CONTRIBUTING.rst
HISTORY.rst
LICENSE
MANIFEST.in
README.rst
setup.cfg
setup.py
askcarl/__init__.py
askcarl/gaussian.py
askcarl/lightgmm.py
askcarl/mixture.py
askcarl/utils.py
askcarl.egg-info/PKG-INFO
askcarl.egg-info/SOURCES.txt
askcarl.egg-info/dependency_links.txt
askcarl.egg-info/requires.txt
askcarl.egg-info/top_level.txt
docs/Makefile
docs/askcarl.rst
docs/conf.py
docs/contributing.rst
docs/index.rst
docs/installation.rst
docs/iris.png
docs/issues.rst
docs/lightgmm.rst
docs/make.bat
docs/modules.rst
docs/readme.rst
tests/test_density.py
tests/test_gaussian.py
tests/test_lightbagginggmm.py
tests/test_lightgmm.py
tests/test_lightgmm2.py
tests/test_utils.py
tests/data/gaussian-dump_COSMOS_z0.002-0.1.npz
tests/data/gaussian-dump_COSMOS_z0.1-0.3.npz
tests/data/gaussian-dump_COSMOS_z0.3-0.5.npz
tests/data/gaussian-dump_COSMOS_z0.5-0.75.npz
tests/data/gaussian-dump_COSMOS_z0.75-1.npz
tests/data/gaussian-dump_COSMOS_z1-1.25.npz
tests/data/gaussian-dump_COSMOS_z1.25-1.5.npz
tests/data/gaussian-dump_COSMOS_z1.5-1.8.npz
tests/data/gaussian-dump_COSMOS_z1.8-2.1.npz
tests/data/gaussian-dump_COSMOS_z2.1-2.7.npz
tests/data/gaussian-dump_COSMOS_z2.7-3.2.npz
tests/data/gaussian-dump_COSMOS_z3.2-4.npz
tests/data/gaussian-dump_COSMOS_z4-7.npz
tests/data/gaussian-dump_eFEDS_z0.002-0.1.npz
tests/data/gaussian-dump_eFEDS_z0.1-0.3.npz
tests/data/gaussian-dump_eFEDS_z0.3-0.5.npz
tests/data/gaussian-dump_eFEDS_z0.5-0.75.npz
tests/data/gaussian-dump_eFEDS_z0.75-1.npz
tests/data/gaussian-dump_eFEDS_z1-1.25.npz
tests/data/gaussian-dump_eFEDS_z1.25-1.5.npz
tests/data/gaussian-dump_eFEDS_z1.5-1.8.npz
tests/data/gaussian-dump_eFEDS_z1.8-2.1.npz
tests/data/gaussian-dump_eFEDS_z2.1-2.7.npz